spendwise_analytics/__init__.py
spendwise_analytics/analytics.py
spendwise_analytics-0.1.1.dist-info/licenses/LICENSE
spendwise_analytics-0.1.1.dist-info/METADATA
spendwise_analytics-0.1.1.dist-info/WHEEL
spendwise_analytics-0.1.1.dist-info/top_level.txt
spendwise_analytics-0.1.1.dist-info/RECORD
