Metadata-Version: 2.4
Name: spendwise-analytics
Version: 0.1.1
Summary: Reusable budgeting projections and checks for Spendwise
Author: Manojkumar
License: MIT
Project-URL: Homepage, https://example.com/spendwise-analytics
Project-URL: Changelog, https://example.com/spendwise-analytics/changelog
Classifier: Programming Language :: Python :: 3
Classifier: License :: OSI Approved :: MIT License
Classifier: Intended Audience :: Developers
Classifier: Topic :: Office/Business :: Financial
Requires-Python: >=3.9
License-File: LICENSE
Dynamic: license-file
